hfsync/__init__.py
hfsync/auth.py
hfsync-0.0.2.dist-info/LICENSE
hfsync-0.0.2.dist-info/METADATA
hfsync-0.0.2.dist-info/WHEEL
hfsync-0.0.2.dist-info/top_level.txt
hfsync-0.0.2.dist-info/RECORD
