Metadata-Version: 2.1
Name: hfsync
Version: 0.0.2
Summary: hfsync
Home-page: http://github.com/trisongz/hfsync
Author: Tri Songz
Author-email: ts@growthengineai.com
License: UNKNOWN
Platform: UNKNOWN
Classifier: Development Status :: 3 - Alpha
Classifier: Environment :: Console
Classifier: Intended Audience :: Developers
Requires-Python: >3.6
Requires-Dist: file-io[cloud]
Requires-Dist: transformers
